cn/__init__.py
cn-0.0.0.0.dist-info/LICENSE
cn-0.0.0.0.dist-info/METADATA
cn-0.0.0.0.dist-info/WHEEL
cn-0.0.0.0.dist-info/top_level.txt
cn-0.0.0.0.dist-info/RECORD
